detdevlib/etl/__init__.py
detdevlib/etl/api.py
detdevlib/etl/azure.py
detdevlib/etl/db/__init__.py
detdevlib/etl/db/_base_manager.py
detdevlib/etl/db/_mssql_manager.py
detdevlib/etl/db/_mysql_manager.py
detdevlib/etl/db/_psql_manager.py
detdevlib/etl/db/_snowflake_manager.py
detdevlib/etl/db/_sqlite_manager.py
detdevlib/etl/df.py
detdevlib/etl/sftp.py
detdevlib/utils/__init__.py
detdevlib/utils/case.py
detdevlib/utils/etc.py
detdevlib/utils/json_pointer.py
detdevlib-1.1.0.dist-info/METADATA
detdevlib-1.1.0.dist-info/WHEEL
detdevlib-1.1.0.dist-info/RECORD
