Metadata-Version: 2.4
Name: detdevlib
Version: 1.1.0
Summary: Internal library to be used across det repositories.
Author: Robert Mertens
Author-email: r.mertens@det.nl
Requires-Python: >=3.11,<4.0
Classifier: Programming Language :: Python :: 3
Classifier: Programming Language :: Python :: 3.11
Classifier: Programming Language :: Python :: 3.12
Classifier: Programming Language :: Python :: 3.13
Classifier: Programming Language :: Python :: 3.14
Requires-Dist: azure-identity (>=1.23.1,<2.0.0)
Requires-Dist: azure-storage-blob (>=12.25.1,<13.0.0)
Requires-Dist: numpy (>=2.3.1,<3.0.0)
Requires-Dist: pandas (>=2.3.0,<3.0.0)
Requires-Dist: paramiko (>=4.0.0,<5.0.0)
Requires-Dist: psycopg2-binary (>=2.9.11,<3.0.0)
Requires-Dist: pydantic (>=2.11.7,<3.0.0)
Requires-Dist: pydantic-settings[dotenv] (>=2.10.1,<3.0.0)
Requires-Dist: pymysql (>=1.1.2,<2.0.0)
Requires-Dist: pyodbc (>=5.3.0,<6.0.0)
Requires-Dist: pytz (>=2025.2,<2026.0)
Requires-Dist: requests (>=2.32.5,<3.0.0)
Requires-Dist: sqlalchemy (>=2.0.41,<3.0.0)
